stateset/__init__.py
stateset/_version.py
stateset/client.py
stateset/errors.py
stateset/py.typed
stateset/types.py
stateset/resources/__init__.py
stateset/resources/base.py
stateset/resources/generic.py
stateset/resources/inventory.py
stateset/resources/orders.py
stateset/resources/returns.py
stateset/resources/warranties.py
stateset/resources/workflows.py
stateset_python-1.2.0.dist-info/licenses/LICENSE
stateset_python-1.2.0.dist-info/METADATA
stateset_python-1.2.0.dist-info/WHEEL
stateset_python-1.2.0.dist-info/top_level.txt
stateset_python-1.2.0.dist-info/RECORD
