Metadata-Version: 2.4
Name: stateset-python
Version: 1.2.0
Summary: Python SDK for the Stateset API - Complete access to returns, warranties, orders, inventory, and work order management
Author-email: StateSet <support@stateset.com>
Maintainer-email: StateSet Team <support@stateset.com>
License-Expression: MIT
Project-URL: Homepage, https://github.com/stateset/stateset-python
Project-URL: Documentation, https://docs.stateset.com/python-sdk
Project-URL: Repository, https://github.com/stateset/stateset-python
Project-URL: Issues, https://github.com/stateset/stateset-python/issues
Project-URL: Changelog, https://github.com/stateset/stateset-python/blob/main/CHANGELOG.md
Keywords: stateset,api,sdk,returns,warranties,orders,inventory,work-orders,maintenance,manufacturing,supply-chain
Classifier: Development Status :: 5 - Production/Stable
Classifier: Intended Audience :: Developers
Classifier: Operating System :: OS Independent
Classifier: Programming Language :: Python :: 3
Classifier: Programming Language :: Python :: 3.8
Classifier: Programming Language :: Python :: 3.9
Classifier: Programming Language :: Python :: 3.10
Classifier: Programming Language :: Python :: 3.11
Classifier: Programming Language :: Python :: 3.12
Classifier: Topic :: Software Development :: Libraries :: Python Modules
Classifier: Topic :: Internet :: WWW/HTTP
Classifier: Topic :: System :: Distributed Computing
Requires-Python: >=3.8
License-File: LICENSE
Requires-Dist: httpx>=0.24.0
Requires-Dist: attrs>=21.3.0
Requires-Dist: typing-extensions>=4.0.0
Provides-Extra: dev
Requires-Dist: pytest>=7.0.0; extra == "dev"
Requires-Dist: pytest-asyncio>=0.20.0; extra == "dev"
Requires-Dist: pytest-cov>=4.0.0; extra == "dev"
Requires-Dist: black>=22.0.0; extra == "dev"
Requires-Dist: isort>=5.0.0; extra == "dev"
Requires-Dist: mypy>=0.990; extra == "dev"
Requires-Dist: pre-commit>=2.20.0; extra == "dev"
Requires-Dist: ruff>=0.1.0; extra == "dev"
Provides-Extra: docs
Requires-Dist: sphinx>=5.0.0; extra == "docs"
Requires-Dist: sphinx-rtd-theme>=1.2.0; extra == "docs"
Requires-Dist: myst-parser>=0.18.0; extra == "docs"
Dynamic: license-file
